LICENSE
MANIFEST.in
README.md
requirements.txt
setup.cfg
setup.py
versioneer.py
pmd_beamphysics/__init__.py
pmd_beamphysics/_version.py
pmd_beamphysics/labels.py
pmd_beamphysics/particles.py
pmd_beamphysics/plot.py
pmd_beamphysics/readers.py
pmd_beamphysics/species.py
pmd_beamphysics/statistics.py
pmd_beamphysics/tools.py
pmd_beamphysics/units.py
pmd_beamphysics/writers.py
pmd_beamphysics.egg-info/PKG-INFO
pmd_beamphysics.egg-info/SOURCES.txt
pmd_beamphysics.egg-info/dependency_links.txt
pmd_beamphysics.egg-info/requires.txt
pmd_beamphysics.egg-info/top_level.txt
pmd_beamphysics/fields/__init__.py
pmd_beamphysics/fields/analysis.py
pmd_beamphysics/fields/expansion.py
pmd_beamphysics/fields/fieldmesh.py
pmd_beamphysics/interfaces/__init__.py
pmd_beamphysics/interfaces/astra.py
pmd_beamphysics/interfaces/bmad.py
pmd_beamphysics/interfaces/elegant.py
pmd_beamphysics/interfaces/genesis.py
pmd_beamphysics/interfaces/gpt.py
pmd_beamphysics/interfaces/impact.py
pmd_beamphysics/interfaces/litrack.py
pmd_beamphysics/interfaces/lucretia.py
pmd_beamphysics/interfaces/opal.py
pmd_beamphysics/interfaces/superfish.py