Metadata-Version: 2.1
Name: pmd-beamphysics
Version: 0.5.6
Summary: UNKNOWN
Home-page: https://github.com/ChristopherMayes/openPMD-beamphysics
License: UNKNOWN
Platform: UNKNOWN
Requires-Python: >=3.6
License-File: LICENSE
